hue_sensors.py
hue_sensors-0.91.dist-info/DESCRIPTION.rst
hue_sensors-0.91.dist-info/METADATA
hue_sensors-0.91.dist-info/RECORD
hue_sensors-0.91.dist-info/WHEEL
hue_sensors-0.91.dist-info/metadata.json
hue_sensors-0.91.dist-info/top_level.txt
