Metadata-Version: 2.0
Name: hue-sensors
Version: 0.91
Summary: Tools for reading the state of Philips Hue sensors
Home-page: https://github.com/robmarkcole/Hue-sensors
Author: Robin Cole
Author-email: robmarkcole@gmail.com
License: MIT
Keywords: hue
Platform: UNKNOWN
Classifier: Development Status :: 4 - Beta
Classifier: Intended Audience :: Developers
Classifier: License :: OSI Approved :: MIT License
Classifier: Natural Language :: English
Classifier: Programming Language :: Python
Classifier: Programming Language :: Python :: 3
Requires-Dist: requests
